{
  "id": "2010422931583860860",
  "url": "https://x.com/getjonwithit/status/2010422931583860860/photo/1",
  "timestamp": "2026-01-11T18:45:53.000Z",
  "capturedAt": "2026-01-12T23:23:29.360Z",
  "author": "Jonathan Gorard @getjonwithit",
  "authorName": "Jonathan Gorard",
  "authorHandle": "@getjonwithit",
  "text": "For anyone curious to see an example of an \"alien mathematics\": here is one of an infinite class of \"logic-like\" systems, with axioms similar (but not equivalent) to those of the NAND operator, and theorems just as rich. On the right is an example of a \"logic-like\" theorem.",
  "avatar": "getjonwithit/avatar/avatar.jpg",
  "avatarPath": "getjonwithit/avatar/avatar.jpg",
  "images": [
    "media/2010422931583860860_G-ZzcOaWMAEMiQJ",
    "media/2010422931583860860_G-Z0NCeXUAAY7kL"
  ],
  "jsonFile": "getjonwithit/tweets/2010422931583860860_2026-01-11-18-45-53.000Z/tweet.json",
  "mediaDir": "media",
  "userSlug": "getjonwithit"
}