{
  "version": 1,
  "items": [
    {
      "url": "https://x.com/sayashk/status/1996334941832089732",
      "note": "",
      "addedAt": "2025-12-03T23:12:24.824Z"
    },
    {
      "url": "https://x.com/deanwball/status/1996346930310328518",
      "note": "",
      "addedAt": "2025-12-03T23:00:11.339Z"
    },
    {
      "url": "https://x.com/fchollet/status/1996277344575840743",
      "note": "",
      "addedAt": "2025-12-03T20:18:43.194Z"
    },
    {
      "url": "https://x.com/Yampeleg/status/1996240295957057864",
      "note": "",
      "addedAt": "2025-12-03T15:58:58.248Z"
    },
    {
      "url": "https://x.com/fchollet/status/1996231823521976582",
      "note": "",
      "addedAt": "2025-12-03T15:57:48.325Z"
    },
    {
      "url": "https://x.com/seconds_0/status/1996042907472863640",
      "note": "",
      "addedAt": "2025-12-03T12:12:25.019Z"
    },
    {
      "url": "https://x.com/aaron_defazio/status/1995978382404903097",
      "note": "",
      "addedAt": "2025-12-03T12:10:48.515Z"
    },
    {
      "url": "https://x.com/deanwball/status/1995875200626295195",
      "note": "",
      "addedAt": "2025-12-03T12:08:22.363Z"
    },
    {
      "url": "https://x.com/fleetingbits/status/1995957069372162501",
      "note": "",
      "addedAt": "2025-12-03T08:09:54.448Z"
    }
  ]
}